<Properties StartupConfiguration="{A7660270-7F4B-4CFF-9C14-8DE3C3D691C9}|Default">
  <MonoDevelop.Ide.Workbench ActiveDocument="SalesWebMvc2/Services/DepartmentService.cs">
    <Files>
      <File FileName="SalesWebMvc2/Views/Sellers/Create.cshtml" />
      <File FileName="SalesWebMvc2/Controllers/SellersController.cs" />
      <File FileName="SalesWebMvc2/Views/Sellers/Details.cshtml" />
      <File FileName="SalesWebMvc2/Views/Departments/Edit.cshtml" />
      <File FileName="SalesWebMvc2/Views/Sellers/Index.cshtml" Line="1" Column="1" />
      <File FileName="SalesWebMvc2/Program.cs" />
      <File FileName="SalesWebMvc2/Views/Departments/Create.cshtml" />
      <File FileName="SalesWebMvc2/Views/Sellers/Delete.cshtml" />
      <File FileName="SalesWebMvc2/Views/Shared/_Layout.cshtml" />
      <File FileName="SalesWebMvc2/Services/SellerService.cs" Line="23" Column="25" />
      <File FileName="SalesWebMvc2/Services/DepartmentService.cs" Line="18" Column="45" />
    </Files>
    <Pads>
      <Pad Id="ProjectPad">
        <State name="__root__">
          <Node name="SalesWebMvc2" expanded="True">
            <Node name="SalesWebMvc2" expanded="True">
              <Node name="Controllers" expanded="True" />
              <Node name="Data" expanded="True" />
              <Node name="Models" expanded="True">
                <Node name="ViewModels" expanded="True" />
              </Node>
              <Node name="Services" expanded="True">
                <Node name="DepartmentService.cs" selected="True" />
              </Node>
              <Node name="Views" expanded="True">
                <Node name="Departments" expanded="True" />
                <Node name="Home" expanded="True" />
                <Node name="Sellers" expanded="True" />
                <Node name="Shared" expanded="True" />
              </Node>
              <Node name="wwwroot" expanded="True">
                <Node name="css" expanded="True" />
              </Node>
            </Node>
          </Node>
        </State>
      </Pad>
    </Pads>
  </MonoDevelop.Ide.Workbench>
  <MonoDevelop.Ide.ItemProperties.SalesWebMvc2 PreferredExecutionTarget="/Applications/Firefox.app" />
  <MonoDevelop.Ide.DebuggingService.PinnedWatches />
  <MonoDevelop.Ide.Workspace ActiveConfiguration="Debug" />
  <MonoDevelop.Ide.DebuggingService.Breakpoints>
    <BreakpointStore />
  </MonoDevelop.Ide.DebuggingService.Breakpoints>
  <MultiItemStartupConfigurations />
</Properties>